.hgignore
.hgtags
55-usb-tmc488.rules
LICENSE
MANIFEST
PyUSBTMC.py
README.rst
README.txt
cPyUSBTMC.pyx
lsusb.py
pci.ids
pyproject.toml
setup.cfg
setup.py
usb.ids
usbids.py
./PyUSBTMC.py
./lsusb.py
./usbids.py
./PyUSBTMC.egg-info/PKG-INFO
./PyUSBTMC.egg-info/SOURCES.txt
./PyUSBTMC.egg-info/dependency_links.txt
./PyUSBTMC.egg-info/requires.txt
./PyUSBTMC.egg-info/top_level.txt
PyUSBTMC.egg-info/PKG-INFO
PyUSBTMC.egg-info/SOURCES.txt
PyUSBTMC.egg-info/dependency_links.txt
PyUSBTMC.egg-info/requires.txt
PyUSBTMC.egg-info/top_level.txt
samples/PyUSBTMC_TEST.py
samples/PyUSBTMC_sample.py
samples/__init__.py
samples/python_usbtmc_sample.py
samples/test_DPO.py
samples/test_dso_anim.py