Metadata-Version: 2.4
Name: PyUSBTMC
Version: 0.2.dev7
Summary: Python module to control USBTMC/USB488 from python/cython
Home-page: http://www-acc.kek.jp/EPICS_Gr/products/
Author: Noboru Yamamoto, KEK, JAPAN
Author-email: "Noboru Yamamoto, KEK, JAPAN" <Noboru.YAMAMOTO@kek.jp>
License-Expression: MIT
Project-URL: Homepage, http://www-acc.kek.jp/EPICS_Gr/products/
Classifier: Programming Language :: Python :: 3
Classifier: Programming Language :: Python :: 3.9
Classifier: Programming Language :: Python :: 3.12
Classifier: Topic :: Scientific/Engineering :: Interface Engine/Protocol Translator
Classifier: Programming Language :: Python :: Implementation :: CPython
Classifier: Operating System :: Unix
Requires-Python: >=3.9
License-File: LICENSE
Requires-Dist: pyusb
Dynamic: author
Dynamic: home-page
Dynamic: license-file
